django_admin_lightweight_date_hierarchy/__init__.py
django_admin_lightweight_date_hierarchy/admin.py
django_admin_lightweight_date_hierarchy/apps.py
django_admin_lightweight_date_hierarchy/models.py
django_admin_lightweight_date_hierarchy/py.typed
django_admin_lightweight_date_hierarchy/templatetags/__init__.py
django_admin_lightweight_date_hierarchy/templatetags/ldh_admin_list.py
django_admin_lightweight_date_hierarchy-1.3.0.dist-info/LICENSE
django_admin_lightweight_date_hierarchy-1.3.0.dist-info/LICENSE.django
django_admin_lightweight_date_hierarchy-1.3.0.dist-info/METADATA
django_admin_lightweight_date_hierarchy-1.3.0.dist-info/WHEEL
django_admin_lightweight_date_hierarchy-1.3.0.dist-info/top_level.txt
django_admin_lightweight_date_hierarchy-1.3.0.dist-info/RECORD
