Metadata-Version: 2.1
Name: django-admin-lightweight-date-hierarchy
Version: 1.3.0
Summary: Use Django Admin date hierarchy queries freely!
Author-email: Haki Benita <hakibenita@gmail.com>
License: MIT, Django
Project-URL: Repository, https://github.com/hakib/django-admin-lightweight-date-hierarchy
Classifier: Development Status :: 5 - Production/Stable
Classifier: Framework :: Django
Classifier: Framework :: Django :: 3.2
Classifier: Framework :: Django :: 4.2
Classifier: Framework :: Django :: 5.0
Classifier: Intended Audience :: Developers
Classifier: License :: OSI Approved :: BSD License
Classifier: Natural Language :: English
Classifier: Programming Language :: Python :: 3.7
Classifier: Programming Language :: Python :: 3.8
Classifier: Programming Language :: Python :: 3.9
Classifier: Programming Language :: Python :: 3.10
Classifier: Programming Language :: Python :: 3.11
Classifier: Programming Language :: Python :: 3.12
Requires-Python: >=3.7
License-File: LICENSE
License-File: LICENSE.django
Requires-Dist: Django >=3.2.0
